{
    "total_closed_trades": 176,
    "win_rate": 61.36,
    "pnl_diario": -0.29,
    "pnl_semanal": 0.0,
    "pnl_mensual": -0.29,
    "pair_ranking": [
        {
            "pair": "BNB/USDT",
            "wins": 48,
            "total": 64,
            "win_rate": 75.0
        },
        {
            "pair": "SOL/USDT",
            "wins": 10,
            "total": 15,
            "win_rate": 66.66666666666666
        },
        {
            "pair": "XRP/USDT",
            "wins": 23,
            "total": 42,
            "win_rate": 54.761904761904766
        },
        {
            "pair": "ETH/USDT",
            "wins": 15,
            "total": 29,
            "win_rate": 51.724137931034484
        },
        {
            "pair": "BTC/USDT",
            "wins": 12,
            "total": 24,
            "win_rate": 50.0
        }
    ],
    "monthly_pnl": [
        {
            "a\u00f1o": 2026,
            "mes": 4,
            "PnL": -0.29,
            "Operaciones": 3
        },
        {
            "a\u00f1o": 2026,
            "mes": 3,
            "PnL": -3.0,
            "Operaciones": 11
        },
        {
            "a\u00f1o": 2026,
            "mes": 2,
            "PnL": -1328.86,
            "Operaciones": 50
        },
        {
            "a\u00f1o": 2026,
            "mes": 1,
            "PnL": 0.4,
            "Operaciones": 36
        },
        {
            "a\u00f1o": 2025,
            "mes": 12,
            "PnL": -755.29,
            "Operaciones": 43
        },
        {
            "a\u00f1o": 2025,
            "mes": 11,
            "PnL": 858.36,
            "Operaciones": 33
        }
    ]
}